FileSystem/__init__.py
FileSystem/file.py
FileSys-1.0.0.dist-info/LICENSE
FileSys-1.0.0.dist-info/METADATA
FileSys-1.0.0.dist-info/WHEEL
FileSys-1.0.0.dist-info/top_level.txt
FileSys-1.0.0.dist-info/RECORD
